LICENSE.txt
README.md
setup.py
ipdtools/__init__.py
ipdtools/ipdModel.py
ipdtools/ipdecode.py
ipdtools/tree_predict.c
ipdtools.egg-info/PKG-INFO
ipdtools.egg-info/SOURCES.txt
ipdtools.egg-info/dependency_links.txt
ipdtools.egg-info/entry_points.txt
ipdtools.egg-info/requires.txt
ipdtools.egg-info/top_level.txt
ipdtools/launchers/__init__.py
ipdtools/launchers/ipdtools_launcher.py
ipdtools/resources/C2.h5
ipdtools/resources/P4-C2.h5
ipdtools/resources/P5-C3.h5
ipdtools/resources/P6-C4.h5
ipdtools/resources/SP2-C2.h5
ipdtools/resources/XL-C2.h5
ipdtools/resources/XL-XL.h5